flask_postgresql/__init__.py
flask_postgresql/postgresql.py
Flask_PostgreSQL-1.1.1.dist-info/LICENSE
Flask_PostgreSQL-1.1.1.dist-info/METADATA
Flask_PostgreSQL-1.1.1.dist-info/WHEEL
Flask_PostgreSQL-1.1.1.dist-info/top_level.txt
Flask_PostgreSQL-1.1.1.dist-info/RECORD
