Metadata-Version: 2.1
Name: Flask-PostgreSQL
Version: 1.1.1
Summary: Flask extension for PostgreSQL
Home-page: https://github.com/kashcode/flask-postgresql
Author: Aleksandrs Kašs
Author-email: aleksandrs.kass@gmail.com
Platform: any
Classifier: Programming Language :: Python :: 3
Classifier: License :: OSI Approved :: MIT License
Classifier: Operating System :: OS Independent
Requires-Python: >=3.6
Provides-Extra: dev
License-File: LICENSE
